AUTHORS
LICENSE
MANIFEST.in
README.md
setup.py
Sharrock.egg-info/PKG-INFO
Sharrock.egg-info/SOURCES.txt
Sharrock.egg-info/dependency_links.txt
Sharrock.egg-info/requires.txt
Sharrock.egg-info/top_level.txt
sharrock/__init__.py
sharrock/client.py
sharrock/descriptors.py
sharrock/modelresource.py
sharrock/models.py
sharrock/registry.py
sharrock/resource_urls.py
sharrock/tests.py
sharrock/urls.py
sharrock/views.py
sharrock/templates/sharrock/descriptor.html
sharrock/templates/sharrock/descriptor.json
sharrock/templates/sharrock/descriptor.xml
sharrock/templates/sharrock/descriptor_body.html
sharrock/templates/sharrock/directory.html
sharrock/templates/sharrock/directory.json
sharrock/templates/sharrock/directory.xml
sharrock/templates/sharrock/resource.json
sharrock/templates/sharrock/resource.xml
sharrock/templates/sharrock/resource_body.html
sharrock/templates/sharrock/resource_directory.html
sharrock/templates/sharrock/resource_directory.json
sharrock/templates/sharrock/resource_directory.xml
sharrock/templates/sharrock/style.html