Metadata-Version: 1.0
Name: Sharrock
Version: 0.6.3.6
Summary: Python remote procedure call framework with server and client components.  RESTful when you need it to be.
Home-page: https://github.com/Axilent/sharrock
Author: Loren Davie
Author-email: code@axilent.com
License: BSD
Platform: UNKNOWN
Classifier: Development Status :: 4 - Beta
Classifier: Environment :: Web Environment
Classifier: Intended Audience :: Developers
Classifier: License :: OSI Approved :: BSD License
Classifier: Programming Language :: Python
Classifier: Topic :: Software Development :: Libraries :: Python Modules
